Workbook

Sheet Cover
B4: ClearLedger Advisory
B6: OtC Transformation
B7: Business Case Builder
B9: Toolkit 3.5 — Strategic Value Series
B11: ROI Calculator · Benefit Quantification · Scenario Analysis · NPV/IRR/Payback
B15: Prepared for: | G15: Prepared by:
B16: [Client Name] | G16: [Consultant Name]
B18: Date: | G18: Version:
B19: [Date] | G19: 1
B22: This workbook provides a structured framework for building a financial business case for Order-to-Cash process transformation. It quantifies costs, benefits, and risks across three scenarios to support investment decisions. All blue-text cells are editable inputs. Formulas auto-calculate all financial metrics.
B27: CONTENTS
B28: 1 | C28: Instructions | D28: How to use this workbook
B29: 2 | C29: Project Setup | D29: Initiative scope, current-state metrics, timeline
B30: 3 | C30: Cost Model | D30: 6-category investment breakdown (one-time + recurring)
B31: 4 | C31: Benefits | D31: 6 benefit categories with DSO→working capital conversion
B32: 5 | C32: Scenarios | D32: Conservative / Base / Optimistic sensitivity analysis
B33: 6 | C33: Financials | D33: NPV, IRR, Payback, 5-year cashflow projection
B34: 7 | C34: Executive Summary | D34: Auto-generated recommendation with key metrics
B35: 8 | C35: Benchmarks | D35: APQC / Hackett OtC performance benchmarks
B36: 9 | C36: Risk Register | D36: Risk identification, scoring, and mitigation
B39: ClearLedger Advisory · Toolkit 3.5 · APQC PCF v7.4: 8.0 Manage Financial Resources

Sheet Instructions
B2: INSTRUCTIONS
B4: Step 1 | C4: Project Setup
C5: Fill in your initiative details: project name, scope, timeline, and current-state AR metrics (revenue, AR balance, DSO, invoice volume, FTE count). All blue-text cells are editable.
B7: Step 2 | C7: Cost Model
C8: Enter one-time and annual recurring costs across 6 categories: Software, Implementation, Internal Labor, Change Management, Infrastructure, and Contingency. Totals auto-calculate.
B10: Step 3 | C10: Benefits
C11: Quantify annual run-rate benefits across 6 categories. For DSO improvement, enter the number of days reduction — the model auto-converts this to working capital release using your revenue figure.
B13: Step 4 | C13: Scenarios
C14: Review and adjust the three scenario assumptions (Conservative = 70% benefits / 120% costs, Base = 100%/100%, Optimistic = 130%/90%). Adjust percentages to match your confidence levels.
B16: Step 5 | C16: Risk Register
C17: Add project risks with probability and impact scores. The weighted risk score feeds into the executive summary.
B19: Step 6 | C19: Review
C20: Check the Financials tab for NPV, IRR, Payback, and ROI across all scenarios. The Executive Summary tab auto-generates a recommendation based on your inputs.
B23: COLOR CODING
C24: Blue text | D24: Editable inputs — your data goes here
C25: Black text | D25: Formulas and calculations (do not edit)
C26: Green highlight | D26: Positive results, favorable metrics
C27: Red highlight | D27: Negative results, areas of concern
C28: Amber highlight | D28: Caution, review recommended
B31: CROSS-REFERENCES
C32: 1.5 KPI Dashboard | D32: DSO, CEI, and AR KPI definitions
C33: 1.6 Maturity Assessment | D33: Tier classification for benefit sizing
C34: 2.1 Credit Management | D34: Bad debt reduction benefit inputs
C35: 2.2 Dispute Resolution | D35: Dispute cost reduction inputs
C36: 2.3 Billing & Invoicing | D36: Invoice processing cost benchmarks
C37: 2.5 Process Mining | D37: Process efficiency gain estimates
C38: 3.3 Treasury & WC | D38: Working capital release calculations
C39: 3.4 Tech Selection | D39: Software and implementation cost inputs

Sheet Project Setup
B2: PROJECT SETUP
B4: ◆ Initiative Details
B5: Project Name | D5: e.g. OtC Automation Program
B6: Executive Sponsor | D6: e.g. CFO / VP Finance
B7: Scope | C7: Full OtC Transformation | D7: Select from dropdown
B8: Industry | C8: Manufacturing | D8: Select from dropdown
B9: Region | C9: Europe | D9: Select from dropdown
B10: Implementation Timeline | C10: 12 | D10: months
B11: Discount Rate (WACC) | C11: 0.1 | D11: Used for NPV calculation
B13: ◎ Current-State Metrics
B14: Annual Revenue (€) | C14: 0 | D14: Total revenue within OtC scope
B15: Accounts Receivable Balance (€) | C15: 0 | D15: Current AR balance
B16: Current DSO | C16: 0 | D16: Days Sales Outstanding
B17: Monthly Invoice Volume | C17: 0 | D17: Invoices processed per month
B18: AR FTE Count | C18: 0 | D18: Full-time equivalents in AR/Collections
B19: Avg Fully-Loaded FTE Cost (€/yr) | C19: 0 | D19: Including benefits, overhead
B21: ◎ DSO Benchmark Position
B22: Your DSO | C22: ='Project Setup'!C16 -> 0
B23: Top Quartile | C23: 28
B24: Median | C24: 38
B25: Bottom Quartile | C25: 52
B26: Source: Hackett Group 2024

Sheet Cost Model
B2: COST MODEL — Investment Breakdown
B4: Category | C4: Description | D4: One-Time (€) | E4: Annual (€) | F4: 5-Year Total (€)
B5: Software / Licensing | C5: ERP modules, automation tools, middleware | D5: 0 | E5: 0 | F5: =D5+E5*5 -> 0
B6: Implementation Services | C6: SI fees, configuration, data migration | D6: 0 | E6: 0 | F6: =D6+E6*5 -> 0
B7: Internal Labor | C7: Project team, SMEs, testing resources | D7: 0 | E7: 0 | F7: =D7+E7*5 -> 0
B8: Change Management | C8: Training, communications, adoption support | D8: 0 | E8: 0 | F8: =D8+E8*5 -> 0
B9: Infrastructure | C9: Cloud hosting, integrations, security | D9: 0 | E9: 0 | F9: =D9+E9*5 -> 0
B10: Contingency | C10: Risk buffer (typically 10-20% of total) | D10: 0 | E10: 0 | F10: =D10+E10*5 -> 0
B11: TOTAL INVESTMENT | D11: =SUM(D5:D10) -> 0 | E11: =SUM(E5:E10) -> 0 | F11: =SUM(F5:F10) -> 0
B13: Cost Distribution
B14: Software / Licensing | C14: =IF(F11=0,0,F5/F11) -> 0
B15: Implementation Services | C15: =IF(F11=0,0,F6/F11) -> 0
B16: Internal Labor | C16: =IF(F11=0,0,F7/F11) -> 0
B17: Change Management | C17: =IF(F11=0,0,F8/F11) -> 0
B18: Infrastructure | C18: =IF(F11=0,0,F9/F11) -> 0
B19: Contingency | C19: =IF(F11=0,0,F10/F11) -> 0

Sheet Benefits
B2: BENEFITS — Quantified Annual Value
B4: Benefit Category | C4: Description | D4: Annual Value (€) | E4: Ramp (months) | F4: Unit
B5: FTE Efficiency Gains | C5: Headcount reduction or redeployment | D5: 0 | E5: 6 | F5: €/yr
B6: DSO Improvement | C6: Working capital release (enter days reduction) | D6: 0 | E6: 9 | F6: days
B7: Error Reduction | C7: Fewer misapplied payments, duplicate invoices | D7: 0 | E7: 3 | F7: €/yr
B8: Dispute Resolution | C8: Faster resolution, reduced write-offs | D8: 0 | E8: 6 | F8: €/yr
B9: Compliance & Audit | C9: Reduced audit prep, SOX compliance savings | D9: 0 | E9: 3 | F9: €/yr
B10: Revenue Protection | C10: Reduced leakage, better credit decisions | D10: 0 | E10: 12 | F10: €/yr
B12: ▲ DSO → Working Capital Impact
B13: DSO days entered | C13: =D6 -> 0
B14: Annual Revenue (from Setup) | C14: ='Project Setup'!C14 -> 0
B15: Working Capital Release (€/yr) | C15: =D6*'Project Setup'!C14/365 -> 0
B16: Formula: DSO reduction × Revenue ÷ 365
B18: TOTAL ANNUAL BENEFIT | C18: =D5+C15+D7+D8+D9+D10 -> 0
B20: Benefit Breakdown
B21: FTE Efficiency | C21: =D5 -> 0 | D21: =IF(C18=0,0,C21/C18) -> 0
B22: DSO / WC Release | C22: =C15 -> 0 | D22: =IF(C18=0,0,C22/C18) -> 0
B23: Error Reduction | C23: =D7 -> 0 | D23: =IF(C18=0,0,C23/C18) -> 0
B24: Dispute Resolution | C24: =D8 -> 0 | D24: =IF(C18=0,0,C24/C18) -> 0
B25: Compliance & Audit | C25: =D9 -> 0 | D25: =IF(C18=0,0,C25/C18) -> 0
B26: Revenue Protection | C26: =D10 -> 0 | D26: =IF(C18=0,0,C26/C18) -> 0

Sheet Scenarios
B2: SCENARIO ANALYSIS
B4: Parameter | C4: Conservative | D4: Base Case | E4: Optimistic
B5: Benefit Realization % | C5: 0.7 | D5: 1 | E5: 1.3
B6: Cost Variance % | C6: 1.2 | D6: 1 | E6: 0.9
B8: Adjusted Annual Benefit (€) | C8: =Benefits!C18*C5 -> 0 | D8: =Benefits!C18*D5 -> 0 | E8: =Benefits!C18*E5 -> 0
B9: Adjusted One-Time Cost (€) | C9: ='Cost Model'!D11*C6 -> 0 | D9: ='Cost Model'!D11*D6 -> 0 | E9: ='Cost Model'!D11*E6 -> 0
B10: Adjusted Annual Cost (€) | C10: ='Cost Model'!E11*C6 -> 0 | D10: ='Cost Model'!E11*D6 -> 0 | E10: ='Cost Model'!E11*E6 -> 0
B12: ◈ Scenario Outputs
B13: Net Annual Cashflow (steady-state) | C13: =C8-C10 -> 0 | D13: =D8-D10 -> 0 | E13: =E8-E10 -> 0
B14: 5-Year Total Benefits | C14: =C8*0.5+C8*4 -> 0 | D14: =D8*0.5+D8*4 -> 0 | E14: =E8*0.5+E8*4 -> 0
B15: 5-Year Total Costs | C15: =C9+C10*5 -> 0 | D15: =D9+D10*5 -> 0 | E15: =E9+E10*5 -> 0
B16: 5-Year Net Value | C16: =C14-C15 -> 0 | D16: =D14-D15 -> 0 | E16: =E14-E15 -> 0
B17: Simple Payback (years) | C17: =IF(C13<=0,"N/A",C9/C13) -> N/A | D17: =IF(D13<=0,"N/A",D9/D13) -> N/A | E17: =IF(E13<=0,"N/A",E9/E13) -> N/A
B18: 5-Year ROI | C18: =IF(C15=0,0,(C14-C15)/C15) -> 0 | D18: =IF(D15=0,0,(D14-D15)/D15) -> 0 | E18: =IF(E15=0,0,(E14-E15)/E15) -> 0

Sheet Financials
B2: FINANCIAL ANALYSIS — Base Case
B4: ◉ Key Investment Metrics
B5: NPV (5-Year) | D5: IRR | F5: Payback Period | H5: 5-Year ROI
B6: =Calculations!B3 -> 0 | D6: =Calculations!B4 -> 0 | F6: =Scenarios!D17 -> N/A | H6: =Scenarios!D18 -> 0
B8: ◉ 5-Year Cashflow Projection — Base Case
B9: Year | C9: Benefits (€) | D9: Costs (€) | E9: Net (€) | F9: Cumulative (€) | G9: Position
B10: Year 0 (Implementation) | C10: — | D10: =Scenarios!D9 -> 0 | E10: =-D10 -> 0 | F10: =E10 -> 0
B11: Year 1 | C11: =Scenarios!D8*0.5 -> 0 | D11: =Scenarios!D10 -> 0 | E11: =C11-D11 -> 0 | F11: =F10+E11 -> 0
B12: Year 2 | C12: =Scenarios!D8 -> 0 | D12: =Scenarios!D10 -> 0 | E12: =C12-D12 -> 0 | F12: =F11+E12 -> 0
B13: Year 3 | C13: =Scenarios!D8 -> 0 | D13: =Scenarios!D10 -> 0 | E13: =C13-D13 -> 0 | F13: =F12+E13 -> 0
B14: Year 4 | C14: =Scenarios!D8 -> 0 | D14: =Scenarios!D10 -> 0 | E14: =C14-D14 -> 0 | F14: =F13+E14 -> 0
B15: Year 5 | C15: =Scenarios!D8 -> 0 | D15: =Scenarios!D10 -> 0 | E15: =C15-D15 -> 0 | F15: =F14+E15 -> 0
B18: ◈ Scenario Comparison
B19: Metric | C19: Conservative | D19: Base Case | E19: Optimistic
B20: Total Investment (5yr) | C20: =Scenarios!C15 -> 0 | D20: =Scenarios!D15 -> 0 | E20: =Scenarios!E15 -> 0
B21: Total Benefits (5yr) | C21: =Scenarios!C14 -> 0 | D21: =Scenarios!D14 -> 0 | E21: =Scenarios!E14 -> 0
B22: 5-Year Net Value | C22: =Scenarios!C16 -> 0 | D22: =Scenarios!D16 -> 0 | E22: =Scenarios!E16 -> 0
B23: Payback Period | C23: =Scenarios!C17 -> N/A | D23: =Scenarios!D17 -> N/A | E23: =Scenarios!E17 -> N/A
B24: 5-Year ROI | C24: =Scenarios!C18 -> 0 | D24: =Scenarios!D18 -> 0 | E24: =Scenarios!E18 -> 0

Sheet Executive Summary
B2: EXECUTIVE SUMMARY
B4: =IF(AND(Calculations!B3>0,Calculations!B4>Calculations!B2),"✓ INVESTMENT RECOMMENDED","⚠ MARGINAL — REVIEW ASSUMPTIONS") -> ⚠ MARGINAL — REVIEW ASSUMPTIONS
B5: =IF('Project Setup'!C5="","OtC Transformation Business Case",'Project Setup'!C5) -> OtC Transformation Business Case
B7: NPV | D7: IRR | F7: Payback | H7: 5-Year ROI
B8: =Calculations!B3 -> 0 | D8: =Calculations!B4 -> 0 | F8: =Scenarios!D17 -> N/A | H8: =Scenarios!D18 -> 0
B10: ◎ Investment vs. Return
B11: One-Time Investment | D11: =Scenarios!D9 -> 0
B12: Annual Recurring Cost | D12: =Scenarios!D10 -> 0
B13: Annual Benefit (run-rate) | D13: =Scenarios!D8 -> 0
B14: 5-Year Total Investment | D14: =Scenarios!D15 -> 0
B15: 5-Year Total Benefits | D15: =Scenarios!D14 -> 0
B16: 5-Year Net Value | D16: =Scenarios!D16 -> 0
B18: ◈ Scenario Range
B19: NPV Range | D19: =Scenarios!C16 -> 0 | E19: to | F19: =Scenarios!E16 -> 0
B20: ROI Range | D20: =Scenarios!C18 -> 0 | E20: to | F20: =Scenarios!E18 -> 0
B21: Weighted Risk Score | D21: =Calculations!B8 -> 0.0634375
B23: Case Robustness | D23: =IF(AND(Scenarios!C16>0,Scenarios!D16>0,Scenarios!E16>0),"Robust across all scenarios",IF(Scenarios!D16>0,"Positive in base case, sensitive to downside","Marginal — reassess assumptions")) -> Marginal — reassess assumptions
B26: ClearLedger Advisory · Toolkit 3.5 · Business Case Builder · APQC PCF v7.4: 8.0

Sheet Benchmarks
B2: APQC / HACKETT OtC BENCHMARKS
B4: Metric | C4: Top Quartile | D4: Median | E4: Bottom Quartile | F4: Source
B5: DSO (days) | C5: 28 | D5: 38 | E5: 52 | F5: Hackett Group 2024
B6: Collection Effectiveness Index (%) | C6: 98 | D6: 92 | E6: 85 | F6: APQC PCF v7.4
B7: Cost per Invoice (€) | C7: 2.1 | D7: 5.4 | E7: 11.2 | F7: Hackett Group 2024
B8: Auto-Match Rate (%) | C8: 92 | D8: 74 | E8: 55 | F8: APQC PCF v7.4
B9: Bad Debt Ratio (%) | C9: 0.1 | D9: 0.4 | E9: 1.2 | F9: Hackett Group 2024
B10: Invoice Accuracy Rate (%) | C10: 99.5 | D10: 97 | E10: 93 | F10: APQC PCF v7.4
B11: Dispute Rate (%) | C11: 1 | D11: 3.5 | E11: 8 | F11: Hackett Group 2024
B12: AR FTE per $1B Revenue | C12: 8 | D12: 15 | E12: 28 | F12: Hackett Group 2024
B13: Electronic Invoice Rate (%) | C13: 95 | D13: 72 | E13: 40 | F13: APQC PCF v7.4
B14: Cash Application Auto-Match (%) | C14: 95 | D14: 78 | E14: 50 | F14: APQC PCF v7.4
B16: Use these benchmarks to validate benefit assumptions. Your DSO, dispute rate, and cost per invoice from Project Setup should be compared against these quartiles to size improvement opportunities realistically.

Sheet Risk Register
B2: RISK REGISTER
B4: # | C4: Risk Description | D4: Probability | E4: Impact | F4: Score | G4: Mitigation Strategy
B5: 1 | C5: Vendor delivery delays | D5: 0.3 | E5: 0.2 | F5: =D5*E5 -> 0.06 | G5: Contractual penalties, phased delivery milestones
B6: 2 | C6: User adoption resistance | D6: 0.4 | E6: 0.3 | F6: =D6*E6 -> 0.12 | G6: Change champions network, iterative training sprints
B7: 3 | C7: Data migration quality issues | D7: 0.25 | E7: 0.25 | F7: =D7*E7 -> 0.0625 | G7: Parallel run period, data quality pre-assessment
B8: 4 | C8: Integration complexity | D8: 0.2 | E8: 0.3 | F8: =D8*E8 -> 0.06 | G8: API-first architecture, middleware layer, POC
B9: 5 | C9: Scope creep | D9: 0.35 | E9: 0.2 | F9: =D9*E9 -> 0.07 | G9: Fixed scope with change request process, steering committee
B10: 6 | C10: Key resource departure | D10: 0.15 | E10: 0.35 | F10: =D10*E10 -> 0.0525 | G10: Knowledge transfer protocols, cross-training, documentation
B11: 7 | C11: Budget overrun | D11: 0.25 | E11: 0.25 | F11: =D11*E11 -> 0.0625 | G11: Monthly burn tracking, contingency release gates
B12: 8 | C12: Regulatory change | D12: 0.1 | E12: 0.2 | F12: =D12*E12 -> 0.02 | G12: Compliance monitoring, modular architecture for updates
F13: =IF(AND(D13<>"",E13<>""),D13*E13,"")
F14: =IF(AND(D14<>"",E14<>""),D14*E14,"")
C16: Weighted Risk Score | F16: =IFERROR(SUMPRODUCT(D5:D14,E5:E14)/COUNTA(C5:C14),0) -> 0.0634375
C18: Scoring Guide:
C19: Low (≤8%) | D19: Acceptable risk, proceed with monitoring
C20: Medium (8-15%) | D20: Active mitigation required, escalate if trending up
C21: High (>15%) | D21: Immediate action needed, may affect business case viability

Sheet Example Data
B2: EXAMPLE DATA — Mid-Market Manufacturer
B4: Use these values to test the model. Copy them into the input sheets.
B6: Project Setup Values
B7: Project Name | C7: AR Automation & Collections Optimization
B8: Executive Sponsor | C8: VP Finance
B9: Scope | C9: Full OtC Transformation
B10: Industry | C10: Manufacturing
B11: Timeline | C11: 12 months
B12: Discount Rate | C12: 10%
B13: Annual Revenue | C13: €120,000,000
B14: AR Balance | C14: €18,000,000
B15: Current DSO | C15: 45 days
B16: Monthly Invoice Volume | C16: 8500
B17: AR FTE Count | C17: 12
B18: Avg FTE Cost | C18: €65,000/yr
B20: Cost Model Values
B21: Software / Licensing | C21: €180,000 one-time / €85,000 annual
B22: Implementation Services | C22: €250,000 one-time / €0 annual
B23: Internal Labor | C23: €120,000 one-time / €30,000 annual
B24: Change Management | C24: €45,000 one-time / €15,000 annual
B25: Infrastructure | C25: €25,000 one-time / €18,000 annual
B26: Contingency (15%) | C26: €93,000 one-time / €22,200 annual
B28: Benefit Values
B29: FTE Efficiency | C29: €195,000/yr (3 FTE redeployed)
B30: DSO Improvement | C30: 8 days reduction
B31: Error Reduction | C31: €72,000/yr
B32: Dispute Resolution | C32: €48,000/yr
B33: Compliance & Audit | C33: €35,000/yr
B34: Revenue Protection | C34: €60,000/yr
B36: Expected Result with Example Data:
B37: Total One-Time Investment | C37: ~€713,000
B38: Total Annual Cost | C38: ~€170,200
B39: Total Annual Benefit (incl. WC) | C39: ~€673,000+
B40: Simple Payback | C40: ~1.4 years
B41: 5-Year ROI | C41: > 100%

Sheet Calculations
A1: CALCULATIONS (HIDDEN)
A2: Discount Rate | B2: ='Project Setup'!C10 -> 12
A3: NPV (Base Case) | B3: =-Scenarios!D9+Financials!E11/((1+B2)^1)+Financials!E12/((1+B2)^2)+Financials!E13/((1+B2)^3)+Financials!E14/((1+B2)^4)+Financials!E15/((1+B2)^5) -> 0
A4: IRR (Base Case) | B4: =IFERROR(IRR(B6:G6),0) -> 0
A6: Cashflows for IRR: | B6: =Financials!E10 -> 0 | C6: =Financials!E11 -> 0 | D6: =Financials!E12 -> 0 | E6: =Financials!E13 -> 0 | F6: =Financials!E14 -> 0 | G6: =Financials!E15 -> 0
A8: Weighted Risk Score | B8: =IFERROR(SUMPRODUCT('Risk Register'!D5:D14,'Risk Register'!E5:E14)/COUNTA('Risk Register'!B5:B14),0) -> 0.0634375

Sheet Dropdowns
A1: DROPDOWN DATA (HIDDEN)
A2: Scope | B2: Industry | C2: Region
A3: Full OtC Transformation | B3: Manufacturing | C3: Europe
A4: AR & Collections Only | B4: Distribution / Wholesale | C4: North America
A5: Billing & Invoicing | B5: Technology / SaaS | C5: Asia-Pacific
A6: Credit Management | B6: Professional Services | C6: Middle East
A7: Cash Application | B7: Retail / E-Commerce | C7: Latin America
A8: Dispute Resolution | B8: Healthcare / Pharma | C8: Global
B9: Financial Services
B10: Energy / Utilities
